Netty4XYonghuZhinan/README.md
Netty4XYonghuZhinan/__init__.py
Netty4XYonghuZhinan/__main__.py
Netty4XYonghuZhinan/file.epub
Netty4XYonghuZhinan/index.html
Netty4XYonghuZhinan/css/__init__.py
Netty4XYonghuZhinan/css/annotations.css
Netty4XYonghuZhinan/css/main.css
Netty4XYonghuZhinan/css/normalize.css
Netty4XYonghuZhinan/css/popup.css
Netty4XYonghuZhinan/font/__init__.py
Netty4XYonghuZhinan/font/fontello.eot
Netty4XYonghuZhinan/font/fontello.svg
Netty4XYonghuZhinan/font/fontello.ttf
Netty4XYonghuZhinan/font/fontello.woff
Netty4XYonghuZhinan/img/__init__.py
Netty4XYonghuZhinan/img/annotator-glyph-sprite.png
Netty4XYonghuZhinan/img/annotator-icon-sprite.png
Netty4XYonghuZhinan/img/apple-touch-icon.png
Netty4XYonghuZhinan/img/cancelfullscreen.png
Netty4XYonghuZhinan/img/close.png
Netty4XYonghuZhinan/img/fullscreen.png
Netty4XYonghuZhinan/img/loader.gif
Netty4XYonghuZhinan/img/menu-icon.png
Netty4XYonghuZhinan/img/save.png
Netty4XYonghuZhinan/img/saved.png
Netty4XYonghuZhinan/img/settings-s.png
Netty4XYonghuZhinan/img/settings.png
Netty4XYonghuZhinan/img/star.png
Netty4XYonghuZhinan/js/__init__.py
Netty4XYonghuZhinan/js/epub.js
Netty4XYonghuZhinan/js/epub.min.js
Netty4XYonghuZhinan/js/epub.min.map
Netty4XYonghuZhinan/js/hooks.min.js
Netty4XYonghuZhinan/js/hooks.min.map
Netty4XYonghuZhinan/js/reader.js
Netty4XYonghuZhinan/js/reader.js.map
Netty4XYonghuZhinan/js/reader.min.js
Netty4XYonghuZhinan/js/reader.min.map
Netty4XYonghuZhinan/js/hooks/__init__.py
Netty4XYonghuZhinan/js/hooks/extensions/__init__.py
Netty4XYonghuZhinan/js/hooks/extensions/highlight.js
Netty4XYonghuZhinan/js/libs/__init__.py
Netty4XYonghuZhinan/js/libs/jquery.min.js
Netty4XYonghuZhinan/js/libs/localforage.min.js
Netty4XYonghuZhinan/js/libs/screenfull.js
Netty4XYonghuZhinan/js/libs/screenfull.min.js
Netty4XYonghuZhinan/js/libs/zip.min.js
Netty4XYonghuZhinan/js/plugins/__init__.py
Netty4XYonghuZhinan/js/plugins/hypothesis.js
Netty4XYonghuZhinan/js/plugins/search.js
netty_4_x_yonghu_zhinan-2024.3.2.0.dist-info/METADATA
netty_4_x_yonghu_zhinan-2024.3.2.0.dist-info/WHEEL
netty_4_x_yonghu_zhinan-2024.3.2.0.dist-info/entry_points.txt
netty_4_x_yonghu_zhinan-2024.3.2.0.dist-info/top_level.txt
netty_4_x_yonghu_zhinan-2024.3.2.0.dist-info/RECORD
